stl/STL10.py
stl/__init__.py
stl/constants.py
stl/dataset_utils.py
stl/download_and_convert_stl10.py
STL10-0.0.4.dist-info/METADATA
STL10-0.0.4.dist-info/WHEEL
STL10-0.0.4.dist-info/top_level.txt
STL10-0.0.4.dist-info/RECORD
