Metadata-Version: 2.1
Name: STL10
Version: 0.0.4
Summary: Easy to use STL10
Author: Shwky Mohamed
Author-email: shwkym54@gmail.com
Keywords: python,ML,dataset,stl-10,STL10
Classifier: Development Status :: 1 - Planning
Classifier: Intended Audience :: Developers
Classifier: Programming Language :: Python :: 3
Classifier: Operating System :: Unix
Classifier: Operating System :: MacOS :: MacOS X
Classifier: Operating System :: Microsoft :: Windows
Requires-Dist: opencv-python
Requires-Dist: tensorflow
Requires-Dist: numpy
